supervisely/README.md
supervisely/__init__.py
supervisely/_utils.py
supervisely/function_wrapper.py
supervisely/sly_logger.py
supervisely/tiny_timer.py
supervisely/versions.json
supervisely/annotation/__init__.py
supervisely/annotation/annotation.py
supervisely/annotation/annotation_transforms.py
supervisely/annotation/json_geometries_map.py
supervisely/annotation/label.py
supervisely/annotation/obj_class.py
supervisely/annotation/obj_class_collection.py
supervisely/annotation/obj_class_mapper.py
supervisely/annotation/renamer.py
supervisely/annotation/tag.py
supervisely/annotation/tag_collection.py
supervisely/annotation/tag_meta.py
supervisely/annotation/tag_meta_collection.py
supervisely/annotation/tag_meta_mapper.py
supervisely/api/__init__.py
supervisely/api/advanced_api.py
supervisely/api/agent_api.py
supervisely/api/annotation_api.py
supervisely/api/api.py
supervisely/api/app_api.py
supervisely/api/constants.py
supervisely/api/dataset_api.py
supervisely/api/entities_collection_api.py
supervisely/api/file_api.py
supervisely/api/github_api.py
supervisely/api/guides_api.py
supervisely/api/image_annotation_tool_api.py
supervisely/api/image_api.py
supervisely/api/import_storage_api.py
supervisely/api/issues_api.py
supervisely/api/labeling_job_api.py
supervisely/api/labeling_queue_api.py
supervisely/api/module_api.py
supervisely/api/object_class_api.py
supervisely/api/plugin_api.py
supervisely/api/project_api.py
supervisely/api/project_class_api.py
supervisely/api/remote_storage_api.py
supervisely/api/report_api.py
supervisely/api/role_api.py
supervisely/api/storage_api.py
supervisely/api/task_api.py
supervisely/api/team_api.py
supervisely/api/user_api.py
supervisely/api/video_annotation_tool_api.py
supervisely/api/workspace_api.py
supervisely/api/entity_annotation/__init__.py
supervisely/api/entity_annotation/entity_annotation_api.py
supervisely/api/entity_annotation/figure_api.py
supervisely/api/entity_annotation/object_api.py
supervisely-6.73.518.dist-info/licenses/LICENSE
supervisely-6.73.518.dist-info/METADATA
supervisely-6.73.518.dist-info/WHEEL
supervisely-6.73.518.dist-info/entry_points.txt
supervisely-6.73.518.dist-info/top_level.txt
supervisely-6.73.518.dist-info/RECORD
