Metadata-Version: 2.4
Name: supervisely
Version: 6.73.518
Summary: Supervisely Python SDK.
Home-page: https://github.com/supervisely/supervisely
Author: Supervisely
Author-email: support@supervisely.com
Maintainer: Max Kolomeychenko
Classifier: Development Status :: 5 - Production/Stable
Classifier: Intended Audience :: Developers
Classifier: Intended Audience :: Science/Research
Classifier: Natural Language :: English
Classifier: Programming Language :: Python :: 3.8
Classifier: Programming Language :: Python :: 3.9
Classifier: Programming Language :: Python :: 3.10
Classifier: Programming Language :: Python :: 3.11
Classifier: Programming Language :: Python :: 3.12
Classifier: Topic :: Scientific/Engineering :: Artificial Intelligence
Classifier: Topic :: Software Development :: Libraries :: Python Modules
Requires-Python: >=3.8
License-File: LICENSE
Requires-Dist: cachetools<=5.5.0,>=4.2.3
Requires-Dist: numpy<=2.3.3,>=1.19
Requires-Dist: opencv-python<5.0.0.0,>=4.6.0.66
Requires-Dist: PTable<1.0.0,>=0.9.2
Requires-Dist: pillow<=10.4.0,>=5.4.1
Requires-Dist: python-json-logger<=3.0.1,>=0.1.11
Requires-Dist: requests<3.0.0,>=2.27.1
Requires-Dist: requests-toolbelt>=0.9.1
Requires-Dist: Shapely<=2.1.2,>=1.7.1
Requires-Dist: bidict<1.0.0,>=0.21.2
Requires-Dist: varname<1.0.0,>=0.8.1
Requires-Dist: python-dotenv<=1.0.1,>=0.19.2
Requires-Dist: pynrrd<1.0.0,>=0.4.2
Requires-Dist: SimpleITK<=2.4.1.0,>=2.1.1.2
Requires-Dist: pydicom<3.0.0,>=2.3.0
Requires-Dist: stringcase<2.0.0,>=1.2.0
Requires-Dist: python-magic<1.0.0,>=0.4.25
Requires-Dist: trimesh<=4.5.0,>=3.11.2
Requires-Dist: uvicorn[standard]<1.0.0,>=0.18.2
Requires-Dist: starlette<=0.47.3
Requires-Dist: pydantic<=2.12.3,>=1.7.4
Requires-Dist: fastapi<=0.119.1,>=0.103.1
Requires-Dist: websockets<=13.1,>=10.3
Requires-Dist: jinja2<4.0.0,>=3.0.3
Requires-Dist: psutil<=7.2.0,>=5.9.0
Requires-Dist: jsonpatch<2.0,>=1.32
Requires-Dist: MarkupSafe<3.0.0,>=2.1.1
Requires-Dist: arel<1.0.0,>=0.2.0
Requires-Dist: tqdm<5.0.0,>=4.62.3
Requires-Dist: pandas<=2.3.3,>=1.1.3
Requires-Dist: async_asgi_testclient
Requires-Dist: PyYAML>=5.4.0
Requires-Dist: distinctipy
Requires-Dist: beautifulsoup4
Requires-Dist: numerize
Requires-Dist: ffmpeg-python==0.2.0
Requires-Dist: python-multipart<=0.0.12,>=0.0.5
Requires-Dist: GitPython
Requires-Dist: giturlparse
Requires-Dist: rich
Requires-Dist: click
Requires-Dist: imutils==0.5.4
Requires-Dist: urllib3<=2.2.3,>=1.26.15
Requires-Dist: cacheout==0.14.1
Requires-Dist: jsonschema<=4.23.0,>=2.6.0
Requires-Dist: pyjwt<3.0.0,>=2.1.0
Requires-Dist: zstd
Requires-Dist: aiofiles
Requires-Dist: httpx[http2]==0.27.2
Requires-Dist: debugpy
Requires-Dist: setuptools<81.0.0
Provides-Extra: extras
Requires-Dist: docker<6.0.0,>=5.0.3; extra == "extras"
Requires-Dist: imagecorruptions<2.0.0,>=1.1.2; extra == "extras"
Requires-Dist: scikit-image<1.0.0,>=0.17.1; extra == "extras"
Requires-Dist: matplotlib<4.0.0,>=3.3.2; extra == "extras"
Requires-Dist: pascal-voc-writer<1.0.0,>=0.1.4; extra == "extras"
Requires-Dist: scipy<2.0.0,>=1.8.0; extra == "extras"
Requires-Dist: pandas<=2.3.3,>=1.1.3; extra == "extras"
Requires-Dist: ruamel.yaml==0.17.21; extra == "extras"
Provides-Extra: apps
Requires-Dist: uvicorn[standard]<1.0.0,>=0.18.2; extra == "apps"
Requires-Dist: fastapi<1.0.0,>=0.79.0; extra == "apps"
Requires-Dist: websockets<=13.1,>=10.3; extra == "apps"
Requires-Dist: jinja2<4.0.0,>=3.0.3; extra == "apps"
Requires-Dist: psutil<6.0.0,>=5.9.0; extra == "apps"
Requires-Dist: jsonpatch<2.0,>=1.32; extra == "apps"
Requires-Dist: MarkupSafe<3.0.0,>=2.1.1; extra == "apps"
Requires-Dist: arel<1.0.0,>=0.2.0; extra == "apps"
Requires-Dist: tqdm<5.0.0,>=4.62.3; extra == "apps"
Requires-Dist: pandas<=2.3.3,>=1.1.3; extra == "apps"
Provides-Extra: docs
Requires-Dist: sphinx==4.4.0; extra == "docs"
Requires-Dist: jinja2==3.0.3; extra == "docs"
Requires-Dist: sphinx-immaterial==0.4.0; extra == "docs"
Requires-Dist: sphinx-copybutton==0.4.0; extra == "docs"
Requires-Dist: sphinx-autodoc-typehints==1.15.3; extra == "docs"
Requires-Dist: sphinxcontrib-details-directive==0.1.0; extra == "docs"
Requires-Dist: myst-parser==0.18.0; extra == "docs"
Provides-Extra: sdk-no-usages
Requires-Dist: grpcio<2.0.0,>=1.53.2; extra == "sdk-no-usages"
Requires-Dist: plotly<6.0.0,>=4.11.0; extra == "sdk-no-usages"
Requires-Dist: psutil<6.0.0,>=5.4.5; extra == "sdk-no-usages"
Provides-Extra: tracking
Requires-Dist: yacs; extra == "tracking"
Requires-Dist: matplotlib<4.0.0,>=3.3.2; extra == "tracking"
Requires-Dist: scipy<2.0.0,>=1.8.0; extra == "tracking"
Requires-Dist: lap; extra == "tracking"
Requires-Dist: cython_bbox; extra == "tracking"
Requires-Dist: termcolor; extra == "tracking"
Requires-Dist: scikit-learn; extra == "tracking"
Requires-Dist: faiss-gpu; extra == "tracking"
Requires-Dist: tabulate; extra == "tracking"
Requires-Dist: tensorboard; extra == "tracking"
Requires-Dist: decord; extra == "tracking"
Requires-Dist: gdown; extra == "tracking"
Requires-Dist: torch; extra == "tracking"
Requires-Dist: motmetrics; extra == "tracking"
Provides-Extra: model-benchmark
Requires-Dist: pycocotools; extra == "model-benchmark"
Requires-Dist: scikit-learn; extra == "model-benchmark"
Requires-Dist: plotly==5.22.0; extra == "model-benchmark"
Requires-Dist: torch; extra == "model-benchmark"
Requires-Dist: torchvision; extra == "model-benchmark"
Provides-Extra: training
Requires-Dist: pycocotools; extra == "training"
Requires-Dist: scikit-learn; extra == "training"
Requires-Dist: plotly==5.22.0; extra == "training"
Requires-Dist: torch; extra == "training"
Requires-Dist: torchvision; extra == "training"
Requires-Dist: tensorboardX; extra == "training"
Requires-Dist: markdown; extra == "training"
Requires-Dist: pymdown-extensions; extra == "training"
Requires-Dist: tbparse; extra == "training"
Requires-Dist: kaleido==0.2.1; extra == "training"
Provides-Extra: plugins
Requires-Dist: jsonschema<3.0.0,>=2.6.0; extra == "plugins"
Provides-Extra: sdk-nn-plugins
Requires-Dist: flask-restful<1.0.0,>=0.3.7; extra == "sdk-nn-plugins"
Requires-Dist: Werkzeug<3.0.0,>=1.0.1; extra == "sdk-nn-plugins"
Provides-Extra: aug
Requires-Dist: imgaug<1.0.0,>=0.4.0; extra == "aug"
Requires-Dist: imagecorruptions<2.0.0,>=1.1.2; extra == "aug"
Requires-Dist: numpy<2.0.0,>=1.19; extra == "aug"
Provides-Extra: agent
Requires-Dist: protobuf<=3.20.3,>=3.19.5; extra == "agent"
Provides-Extra: versioning
Requires-Dist: pyarrow<=22.0.0,>=17.0.0; extra == "versioning"
Dynamic: author
Dynamic: author-email
Dynamic: classifier
Dynamic: description
Dynamic: description-content-type
Dynamic: home-page
Dynamic: license-file
Dynamic: maintainer
Dynamic: provides-extra
Dynamic: requires-dist
Dynamic: requires-python
Dynamic: summary
